d_probability
