Metadata-Version: 2.1
Name: d-probability
Version: 0.5
Summary: Gaussian distributions
Home-page: UNKNOWN
Author: Nilayan Bose
License: UNKNOWN
Platform: UNKNOWN
Classifier: Programming Language :: Python :: 3
Classifier: License :: OSI Approved :: MIT License
Classifier: Operating System :: OS Independent
